CHANGELOG.rst
MANIFEST.in
README.rst
setup.cfg
setup.py
docs/Makefile
docs/conf.py
docs/index.rst
docs/intro.rst
docs/quickstart.rst
docs/toc.rst
mfw_template/__init__.py
mfw_template/cli.py
mfw_template.egg-info/PKG-INFO
mfw_template.egg-info/SOURCES.txt
mfw_template.egg-info/dependency_links.txt
mfw_template.egg-info/entry_points.txt
mfw_template.egg-info/not-zip-safe
mfw_template.egg-info/requires.txt
mfw_template.egg-info/top_level.txt
mfw_template/commands/__init__.py
mfw_template/commands/create_applicationbehavior.py
mfw_template/commands/create_behavior.py
mfw_template/commands/create_fieldvalidator.py
mfw_template/commands/create_formvalidator.py
mfw_template/commands/create_project.py
mfw_template/commands/create_resource.py
mfw_template/templates/applicationbehavior/cookiecutter.json
mfw_template/templates/applicationbehavior/hooks/post_gen_project.py
mfw_template/templates/applicationbehavior/{{cookiecutter.module_name}}/__init__.py
mfw_template/templates/applicationbehavior/{{cookiecutter.module_name}}/applicationbehavior.py
mfw_template/templates/applicationbehavior/{{cookiecutter.module_name}}/model.py
mfw_template/templates/applicationbehavior/{{cookiecutter.module_name}}/modelui.py
mfw_template/templates/behavior/cookiecutter.json
mfw_template/templates/behavior/hooks/post_gen_project.py
mfw_template/templates/behavior/{{cookiecutter.module_name}}/__init__.py
mfw_template/templates/behavior/{{cookiecutter.module_name}}/behavior.py
mfw_template/templates/behavior/{{cookiecutter.module_name}}/model.py
mfw_template/templates/behavior/{{cookiecutter.module_name}}/modelui.py
mfw_template/templates/behavior/{{cookiecutter.module_name}}/schema.py
mfw_template/templates/fieldvalidator/cookiecutter.json
mfw_template/templates/fieldvalidator/hooks/post_gen_project.py
mfw_template/templates/fieldvalidator/{{ cookiecutter.module_container }}/__init__.py
mfw_template/templates/fieldvalidator/{{ cookiecutter.module_container }}/{{cookiecutter.module_name}}.py
mfw_template/templates/formvalidator/cookiecutter.json
mfw_template/templates/formvalidator/hooks/post_gen_project.py
mfw_template/templates/formvalidator/{{ cookiecutter.module_container }}/__init__.py
