Metadata-Version: 2.1
Name: mfw-template
Version: 0.3
Summary: Cookiecutter templates for Morp Framework
Home-page: http://github.com/morpframework
Author: Izhar Firdaus
Author-email: kagesenshi.87@gmail.com
License: MIT
Platform: UNKNOWN
Provides-Extra: docs
